django_db_conn_pool/__init__.py
django_db_conn_pool/mysqlalchemy/__init__.py
django_db_conn_pool/mysqlalchemy/base.py
django_db_conn_pool/mysqlalchemy/conf.py
django_db_conn_pool/mysqlalchemy/pool.py
django_db_conn_pool-1.0.0.dist-info/LICENSE
django_db_conn_pool-1.0.0.dist-info/METADATA
django_db_conn_pool-1.0.0.dist-info/WHEEL
django_db_conn_pool-1.0.0.dist-info/top_level.txt
django_db_conn_pool-1.0.0.dist-info/RECORD
