Metadata-Version: 2.1
Name: django-db-conn-pool
Version: 1.0.0
Summary: Gevent-Friendly Database Connection Pooling in Django
Home-page: https://github.com/shzhao17/django-db-conn-pool
Author: Patrick Zhao
License: Apache 2.0
Platform: UNKNOWN
Classifier: Development Status :: 5 - Production/Stable
Classifier: Intended Audience :: Developers
Classifier: Natural Language :: English
Classifier: License :: OSI Approved :: Apache Software License
Classifier: Programming Language :: Python
Classifier: Programming Language :: Python :: 2.7
Classifier: Programming Language :: Python :: Implementation :: CPython
Requires-Python: >=2.7,<3
Requires-Dist: six
Requires-Dist: typing
Requires-Dist: django
Requires-Dist: sqlalchemy
